talk2dom/__init__.py
talk2dom/client.py
talk2dom/exceptions.py
talk2dom/models.py
talk2dom/playwright.py
talk2dom/selenium.py
talk2dom/utils.py
talk2dom/version.py
talk2dom-0.3.5.dist-info/licenses/LICENSE
talk2dom-0.3.5.dist-info/METADATA
talk2dom-0.3.5.dist-info/WHEEL
talk2dom-0.3.5.dist-info/top_level.txt
talk2dom-0.3.5.dist-info/RECORD
