Metadata-Version: 2.4
Name: talk2dom
Version: 0.3.5
Summary: Minimal Python client for Talk2Dom API (natural-language DOM locator).
Author: Talk2Dom
License:                                  Apache License
Project-URL: Homepage, https://talk2dom.itbanque.com
Project-URL: Repository, https://github.com/itbanque/talk2dom-python
Requires-Python: >=3.9
License-File: LICENSE
Requires-Dist: httpx>=0.25
Requires-Dist: loguru>=0.7.3
Requires-Dist: beautifulsoup4>=4.13.5
Provides-Extra: selenium
Requires-Dist: selenium>=4.0; extra == "selenium"
Provides-Extra: playwright
Requires-Dist: playwright>=1.40; extra == "playwright"
Dynamic: license-file
